zilib-0.1.11.dist-info/METADATA
zilib-0.1.11.dist-info/WHEEL
zilib/lists/hfhchan-kVariants.txt
zilib/lists/wordshk_autoconvert.json
zilib/lists/TWVariants.txt
zilib/lists/wordshk_variantmap.json
zilib/lists/wordshk_autoconvert.txt
zilib/lists/edb_charlist.txt
zilib/lists/wordshk_charset.json
zilib/lists/wordslist.csv
zilib/lists/wordshk_variantmap.txt
zilib/lists/index.md
zilib/lists/wordshk_charlist.txt
zilib/lists/CJKRadicals.txt
zilib/lists/HKVariants.txt
zilib/lists/charlist.json
zilib/lists/english_variants.json
zilib/__init__.py
zilib/zilib.cpython-39-darwin.so
zilib-0.1.11.dist-info/RECORD
